modelmarket/__init__.py
modelmarket/modelmarket.py
modelmarket-0.1.76.dist-info/METADATA
modelmarket-0.1.76.dist-info/WHEEL
modelmarket-0.1.76.dist-info/RECORD
